{
  "HyundaiIoniq6": {
    "id": "20",
    "price": "45",
    "img": "../Assets/images/Hyundai.png",
    "model": "A1",
    "mark": "Audi",
    "year": "2019",
    "doors": "4/5",
    "AC": "Yes",
    "transmission": "Automatic",
    "fuel": "Gasoline"
  },
  "ChevroletCorvetteZ06": {
    "id": "21",
    "price": "80",
    "img": "../Assets/images/chevrolet.png",
    "model": "Corvette Z06",
    "mark": "Chevrolet",
    "year": "2014",
    "doors": "2",
    "AC": "Yes",
    "transmission": "Manual",
    "fuel": "Gasoline"
  },
  "KiaEV6": {
    "id": "22",
    "price": "35",
    "img": "../Assets/images/Kia.png",
    "model": "Kia EV6",
    "mark": "Kia",
    "year": "2018",
    "doors": "4",
    "AC": "Yes",
    "transmission": "Automatic",
    "fuel": "Electric"
  },
  "AudiA6": {
    "id": "23",
    "price": "50",
    "img": "../Assets/images/Audi_A6.png",
    "model": "A6",
    "mark": "Audi",
    "year": "2016",
    "doors": "4",
    "AC": "Yes",
    "transmission": "Automatic",
    "fuel": "Gasoline"
  },
  "AudiA6Allroad": {
    "id": "24",
    "price": "65",
    "img": "../Assets/images/Audi_All.png",
    "model": "A6 Allroad",
    "mark": "Audi",
    "year": "2020",
    "doors": "5",
    "AC": "Yes",
    "transmission": "Automatic",
    "fuel": "Gasoline"
  },
  "BMWM4CSL": {
    "id": "25",
    "price": "85",
    "img": "../Assets/images/BMW.png",
    "model": "M4 CSL",
    "mark": "BMW",
    "year": "2015",
    "doors": "2",
    "AC": "Yes",
    "transmission": "Manual",
    "fuel": "Gasoline"
  }
}
